README.rst
setup.py
src/symboldict/__init__.py
src/symboldict/version.py
src/symboldict.egg-info/PKG-INFO
src/symboldict.egg-info/SOURCES.txt
src/symboldict.egg-info/dependency_links.txt
src/symboldict.egg-info/entry_points.txt
src/symboldict.egg-info/top_level.txt